ipackage/iplocation.py
ipackage-0.1.0.dist-info/METADATA
ipackage-0.1.0.dist-info/WHEEL
ipackage-0.1.0.dist-info/top_level.txt
ipackage-0.1.0.dist-info/RECORD
